magicattr.py
magicattr-0.1.4.dist-info/METADATA
magicattr-0.1.4.dist-info/RECORD
magicattr-0.1.4.dist-info/WHEEL
magicattr-0.1.4.dist-info/top_level.txt
