Metadata-Version: 2.1
Name: magicattr
Version: 0.1.4
Summary: A getattr and setattr that works on nested objects, lists, dicts, and any combination thereof without resorting to eval
Home-page: https://github.com/frmdstryr/magicattr
Author: frmdstryr
Author-email: frmdstryr@gmail.com
License: MIT
Platform: UNKNOWN
